setup.py
app/__init__.py
app/secrets_gen.py
delineasecrets.egg-info/PKG-INFO
delineasecrets.egg-info/SOURCES.txt
delineasecrets.egg-info/dependency_links.txt
delineasecrets.egg-info/top_level.txt